nautobot_prometheus_sd/__init__.py
nautobot_prometheus_sd/api/__init__.py
nautobot_prometheus_sd/api/serializers.py
nautobot_prometheus_sd/api/urls.py
nautobot_prometheus_sd/api/utils.py
nautobot_prometheus_sd/api/views.py
nautobot_prometheus_sd/tests/__init__.py
nautobot_prometheus_sd/tests/test_api.py
nautobot_prometheus_sd/tests/test_serializers.py
nautobot_prometheus_sd/tests/utils.py
nautobot_plugin_prometheus_sd-0.0.0.dist-info/LICENSE
nautobot_plugin_prometheus_sd-0.0.0.dist-info/WHEEL
nautobot_plugin_prometheus_sd-0.0.0.dist-info/METADATA
nautobot_plugin_prometheus_sd-0.0.0.dist-info/RECORD
